pattern_detector/__init__.py
pattern_detector/aoi_finder.py
pattern_detector/cosine_similarity_function.py
pattern_detector/sliding_window_cosine_similarity.py
pattern_detector/utils.py
tests/__init__.py
tests/test_detector.py
pattern_detector-0.2.2.dist-info/LICENSE
pattern_detector-0.2.2.dist-info/METADATA
pattern_detector-0.2.2.dist-info/WHEEL
pattern_detector-0.2.2.dist-info/top_level.txt
pattern_detector-0.2.2.dist-info/RECORD
