Metadata-Version: 2.2
Name: pattern_detector
Version: 0.2.2
Summary: A library for detecting patterns in time-series data.
Author: Yigit Utku Bulut and Ahmet Faruk Minareci
Author-email: yigit.utku.bulut@gmail.com, ahmetfaruk.minareci@gmail.com
License: MIT
Classifier: Programming Language :: Python :: 3
Classifier: License :: OSI Approved :: MIT License
Classifier: Operating System :: OS Independent
Requires-Python: >=3.7
License-File: LICENSE
Requires-Dist: numpy
Requires-Dist: pandas
Requires-Dist: joblib
Requires-Dist: scipy
Dynamic: author
Dynamic: author-email
Dynamic: classifier
Dynamic: description
Dynamic: description-content-type
Dynamic: license
Dynamic: requires-dist
Dynamic: requires-python
Dynamic: summary
